best/__init__.py
best/model.py
best/plot.py
best-2.0.5.dist-info/LICENSE
best-2.0.5.dist-info/METADATA
best-2.0.5.dist-info/WHEEL
best-2.0.5.dist-info/top_level.txt
best-2.0.5.dist-info/RECORD
