Metadata-Version: 2.1
Name: best
Version: 2.0.5
Summary: Bayesian estimation supersedes the t-test
Home-page: https://github.com/treszkai/best
Author: Andrew Straw and Laszlo Treszkai
Author-email: laszlo.treszkai@gmail.com
License: MIT
Classifier: Programming Language :: Python :: 3
Classifier: License :: OSI Approved :: MIT License
Classifier: Operating System :: OS Independent
Requires-Python: >=3.7
License-File: LICENSE
Requires-Dist: arviz (>=0.2.0)
Requires-Dist: numpy
Requires-Dist: scipy
Requires-Dist: matplotlib (>=3.0.0)
Requires-Dist: pymc3 (<4.0)
